README.md
ruff_auto_flash.py
setup.py
ruff_auto_flash.egg-info/PKG-INFO
ruff_auto_flash.egg-info/SOURCES.txt
ruff_auto_flash.egg-info/dependency_links.txt
ruff_auto_flash.egg-info/requires.txt
ruff_auto_flash.egg-info/top_level.txt