Metadata-Version: 1.0
Name: ruff-auto-flash
Version: 0.0.12
Summary: ruff auto flash
Home-page: http://git.nanchao.org:3000/wangqj/auto_flash.git
Author: wangqj
Author-email: wangqinjun@nanchao.org
License: UNKNOWN
Platform: UNKNOWN
